route_knorket/__init__.py
route_knorket/cli.py
route_knorket/main.py
route_knorket-0.6.0.dist-info/METADATA
route_knorket-0.6.0.dist-info/WHEEL
route_knorket-0.6.0.dist-info/entry_points.txt
route_knorket-0.6.0.dist-info/top_level.txt
route_knorket-0.6.0.dist-info/RECORD
