Metadata-Version: 2.1
Name: route_knorket
Version: 0.6.0
Summary: Knorket router exposes internal private services via zero-trust
Home-page: 
Author: ockhamlabs
Author-email: hello@ockhamlabs.ai
Classifier: Programming Language :: Python :: 3
Classifier: License :: OSI Approved :: MIT License
Classifier: Operating System :: OS Independent
Requires-Python: >=3.6
Requires-Dist: requests
Requires-Dist: pylint
Requires-Dist: pylint-exit
Requires-Dist: pyinstaller
Requires-Dist: tqdm
Requires-Dist: psutil
Requires-Dist: packaging
Requires-Dist: pyjwt
Requires-Dist: colorama
Requires-Dist: jinja2
Requires-Dist: distro
Requires-Dist: pyyaml
